bcrp_webscrapper/__init__.py
bcrp_webscrapper/bcrp.py
bcrp_webscrapper-1.0.6.dist-info/LICENSE
bcrp_webscrapper-1.0.6.dist-info/METADATA
bcrp_webscrapper-1.0.6.dist-info/WHEEL
bcrp_webscrapper-1.0.6.dist-info/top_level.txt
bcrp_webscrapper-1.0.6.dist-info/RECORD
