Metadata-Version: 2.1
Name: bcrp_webscrapper
Version: 1.0.6
Summary: Time series extraction from the Peruvian Central Bank Database (BCRP Statistics)
Home-page: https://github.com/estcab00/bcrp-webscrapper
Author: Esteban Cabrera
Classifier: Programming Language :: Python :: 3
Classifier: License :: OSI Approved :: MIT License
Classifier: Operating System :: OS Independent
Requires-Python: >=3.6
License-File: LICENSE
Requires-Dist: pandas
Requires-Dist: numpy
Requires-Dist: requests
Requires-Dist: unidecode
Requires-Dist: selenium
Requires-Dist: openpyxl
Requires-Dist: more-itertools
Requires-Dist: webdriver-manager
